{
  "date": "2026-06-18",
  "generated_at_utc": "2026-06-18T02:04:00Z",
  "generated_at_bjt": "2026-06-18 10:04",
  "methodology": "ESPN API spread/total open→close line movement only. Calibration: 50% draws in last 14 games, hot-favorite-draw pattern. No score correction.",
  "retrospective": {
    "note": "predictions/ directory empty, no prior predictions to grade. Observed past 24h: 3 home wins, 1 draw, 0 away wins. Hot-favorite-draw trend (6 prior) BROKEN — Portugal 1-1 DR Congo is NOT a hot-favorite draw (Portugal was heavy favorite but still drew; however the streak of expected-wins-not-happening pauses). England 4-2 Croatia shows strong team with line movement can win.",
    "calibration": "Hold: hot-favorite-draw caution remains valid (Portugal still drew). Confirmed: strong spread+total dual signal still reliable for big favorites (CAN -360 with over support = bettable)."
  },
  "predictions": [
    {
      "match": "South Africa vs Czechia",
      "kickoff_bjt": "2026-06-19 00:00",
      "kickoff_utc": "2026-06-18T16:00Z",
      "pick": "Draw",
      "confidence": 2,
      "confidence_stars": "⭐⭐",
      "predicted_score": "1-1",
      "asian_handicap": "CZE -0.5 @ -125",
      "ou": "Under 2.5 @ -135",
      "btts": "No",
      "line_movement_summary": "CZE spread -110→-125 (mild home support); RSA spread -125→+100 (away gaining value); under still strong -165→-135. Mixed signals + hot-favorite-draw pattern → lean draw."
    },
    {
      "match": "Bosnia-Herzegovina vs Switzerland",
      "kickoff_bjt": "2026-06-19 03:00",
      "kickoff_utc": "2026-06-18T19:00Z",
      "pick": "Switzerland win",
      "confidence": 3,
      "confidence_stars": "⭐⭐⭐",
      "predicted_score": "2-0",
      "asian_handicap": "SUI -0.5 @ -185",
      "ou": "Under 2.5 @ -125",
      "btts": "No",
      "line_movement_summary": "MASSIVE shift: SUI spread moved -1.5→-0.5 AND odds from +135→-185. Market now treats SUI as dominant 0.5-goal favorite. Total flat (no signal). Spread-only signal caps at ⭐⭐⭐ (need both signals for ⭐⭐⭐⭐)."
    },
    {
      "match": "Qatar vs Canada",
      "kickoff_bjt": "2026-06-19 06:00",
      "kickoff_utc": "2026-06-18T22:00Z",
      "pick": "Canada win",
      "confidence": 4,
      "confidence_stars": "⭐⭐⭐⭐",
      "predicted_score": "2-0",
      "asian_handicap": "CAN -1.5 @ -125",
      "ou": "Over 2.5 @ -145",
      "btts": "No",
      "line_movement_summary": "DUAL STRONG SIGNAL: spread CAN -1.5 with odds +125→-125 (massive home support) + total over odds +110→-145 (massive over support). Both signals align. CAN -360 ML confirms dominance. Only ⭐⭐⭐⭐ pick in this batch."
    },
    {
      "match": "South Korea vs Mexico",
      "kickoff_bjt": "2026-06-19 09:00",
      "kickoff_utc": "2026-06-19T01:00Z",
      "pick": "Draw",
      "confidence": 2,
      "confidence_stars": "⭐⭐",
      "predicted_score": "1-1",
      "asian_handicap": "MEX -0.5 @ -105",
      "ou": "Under 2.5 @ -170",
      "btts": "Yes",
      "line_movement_summary": "MEX spread -0.5 WEAKENING (-135→-105); KOR spread gaining (+100→-125). Under strong -150→-170. Hot-favorite-draw pattern + MEX weakening → lean draw 1-1."
    }
  ],
  "summary": "1 ⭐⭐⭐⭐ pick (CAN) + 1 ⭐⭐⭐ (SUI) + 2 ⭐⭐ (CZE/RSA, MEX/KOR). Total: 4 matches within 24h BJT window.",
  "tournament_context": "Tournament trends reference: tournament-trends.md notes consecutive hot-favorite draws through 06-16. Last 24h broke streak: Portugal drew (still hot-fav draw), but England 4-2 Croatia and Austria 3-1 Jordan are home wins. Pattern: home teams winning 3/4 in last 24h."
}